mlmarker/__init__.py
mlmarker/constants.py
mlmarker/explainability.py
mlmarker/model.py
mlmarker/models/TP_features_full_quant_update_20241216.txt
mlmarker/models/TP_features_full_quant_update_20250113.txt
mlmarker/models/TP_full_92%_10exp_2024.joblib
mlmarker/models/TP_full_quant_update_20241216.joblib
mlmarker/models/TP_full_quant_update_20250113.joblib
mlmarker/models/binary_TP_4000features_95to75missingness_2024.joblib
mlmarker/models/binary_features_TP_4000features_95to75missingness_2024.txt
mlmarker/models/features_TP_full_92%_10exp_2024.txt
mlmarker/utils.py
mlmarker-0.1.6.dist-info/LICENSE
mlmarker-0.1.6.dist-info/METADATA
mlmarker-0.1.6.dist-info/WHEEL
mlmarker-0.1.6.dist-info/RECORD
