Metadata-Version: 2.3
Name: mlmarker
Version: 0.1.6
Summary: 
Author: TineClaeys
Author-email: tineclae.claeys@ugent.be
Requires-Python: >=3.7,<4.0
Classifier: Programming Language :: Python :: 3
Classifier: Programming Language :: Python :: 3.7
Classifier: Programming Language :: Python :: 3.8
Classifier: Programming Language :: Python :: 3.9
Classifier: Programming Language :: Python :: 3.10
Classifier: Programming Language :: Python :: 3.11
Classifier: Programming Language :: Python :: 3.12
Classifier: Programming Language :: Python :: 3.13
Requires-Dist: ace
Requires-Dist: bioservices
Requires-Dist: dask
Requires-Dist: datashader
Requires-Dist: easydev
Requires-Dist: gprofiler-official
Requires-Dist: joblib
Requires-Dist: matplotlib
Requires-Dist: numpy (==1.23.5)
Requires-Dist: pandas
Requires-Dist: plotly
Requires-Dist: scikit-learn
Requires-Dist: scipy
Requires-Dist: seaborn
Requires-Dist: shap (==0.42.0)
Requires-Dist: umap-learn
